AUTHORS
CHANGELOG.rst
LICENSE
MANIFEST.in
Makefile
README.rst
setup.py
examples/project/__init__.py
examples/project/manage.py
examples/project/settings.py
examples/project/urls.py
examples/project/templates/404.html
examples/project/templates/500.html
examples/project/zoo/__init__.py
examples/project/zoo/models.py
examples/project/zoo/test_doctest_modules.py
examples/project/zoo/test_fixtures.py
examples/project/zoo/test_race.py
examples/project/zoo/test_urlconf.py
examples/project/zoo/tests.py
examples/project/zoo/urls.py
examples/project/zoo/views.py
nosedjango/__init__.py
nosedjango/nosedjango.py
nosedjango.egg-info/PKG-INFO
nosedjango.egg-info/SOURCES.txt
nosedjango.egg-info/dependency_links.txt
nosedjango.egg-info/entry_points.txt
nosedjango.egg-info/not-zip-safe
nosedjango.egg-info/requires.txt
nosedjango.egg-info/top_level.txt
nosedjango/plugins/__init__.py
nosedjango/plugins/base_plugin.py
nosedjango/plugins/celery_plugin.py
nosedjango/plugins/cherrypy_plugin.py
nosedjango/plugins/file_storage_plugin.py
nosedjango/plugins/selenium_plugin.py
nosedjango/plugins/settings_target_plugin.py
nosedjango/plugins/sphinxsearch_plugin.py
nosedjango/plugins/sqlite_plugin.py
nosedjango/plugins/ssh_tunnel_plugin.py
nosedjangotests/__init__.py
nosedjangotests/manage.py
nosedjangotests/settings.py
nosedjangotests/settings_legacy.py
nosedjangotests/urls.py
nosedjangotests/polls/__init__.py
nosedjangotests/polls/helpers.py
nosedjangotests/polls/models.py
nosedjangotests/polls/fixtures/choices.json
nosedjangotests/polls/fixtures/polls1.json
nosedjangotests/polls/fixtures/polls2.json
nosedjangotests/polls/management/__init__.py
nosedjangotests/polls/management/commands/__init__.py
nosedjangotests/polls/management/commands/syncdb.py
nosedjangotests/polls/migrations/0001_initial.py
nosedjangotests/polls/migrations/__init__.py
nosedjangotests/polls/south_migrations/0001_initial.py
nosedjangotests/polls/south_migrations/__init__.py
nosedjangotests/polls/tests/__init__.py
nosedjangotests/polls/tests/test0.py
nosedjangotests/polls/tests/test1.py
nosedjangotests/polls/tests/test2.py
nosedjangotests/polls/tests/test_custom_client.py
nosedjangotests/polls/tests/test_dummy_decorator.py
