Metadata-Version: 1.0
Name: nosedjango
Version: 1.1.0
Summary:  nosedjango cranks up the awesome for your Django project by giving you all the testing goodness of the Nose ecosystem. Use multiprocess, xunit, coverage, etc or even write your own plugin that hooks in to the NoseDjango plugin system (a plugin with a plugin system!) 
Home-page: http://github.com/nosedjango/nosedjango
Author: Wes Winham
Author-email: winhamwr@gmail.com
License: GNU LGPL
Platform: UNKNOWN
